icsecontrib/__init__.py
icsecontrib/sagecellserver.py
icsecontrib_sagecellserver-1.3.dist-info/METADATA
icsecontrib_sagecellserver-1.3.dist-info/WHEEL
icsecontrib_sagecellserver-1.3.dist-info/top_level.txt
icsecontrib_sagecellserver-1.3.dist-info/RECORD
