Metadata-Version: 2.1
Name: icsecontrib-sagecellserver
Version: 1.3
Summary: Sphinx sagecellserver extension
Home-page: https://github.com/pypa/sampleproject
Author: Krzysztof Kajda
Author-email: kajda.krzysztof@gmail.com
License: UNKNOWN
Project-URL: Bug Tracker, https://github.com/kriskda/sphinx-sagecell
Platform: UNKNOWN
Classifier: Programming Language :: Python :: 3
Classifier: License :: OSI Approved :: MIT License
Classifier: Operating System :: OS Independent
Requires-Python: >=3.6
